{
  "aedt_dir": "parrarel2",
  "xformer_type": 0,
  "per": 3000,
  "freq_khz": 140,
  "is_validated": true,
  "data": {
    "simulation parameter": {
      "A [mm]": {
        "0": 59.6
      },
      "B [mm]": {
        "0": 43.2
      },
      "C [mm]": {
        "0": 10.4
      },
      "core_N_w1 [mm]": {
        "0": 4
      },
      "core_P_w1 [mm]": {
        "0": 14
      },
      "D [mm]": {
        "0": 17.4
      },
      "E [mm]": {
        "0": 6.8
      },
      "g1 [mm]": {
        "0": 0.1
      },
      "g2 [mm]": {
        "0": 0.3
      },
      "h1 [mm]": {
        "0": 13.6
      },
      "l1_center [mm]": {
        "0": 10.4
      },
      "l1_leg [mm]": {
        "0": 8.2
      },
      "l1_top [mm]": {
        "0": 10.6
      },
      "l2 [mm]": {
        "0": 16.4
      },
      "l2_tap [mm]": {
        "0": 0
      },
      "ratio [mm]": {
        "0": 0.51
      },
      "Rx_height [mm]": {
        "0": 0.175
      },
      "Rx_hTurns []": {
        "0": 1
      },
      "Rx_layer_space_x [mm]": {
        "0": 2.9
      },
      "Rx_layer_space_y [mm]": {
        "0": 1.9
      },
      "Rx_preg [mm]": {
        "0": 0.01
      },
      "Rx_space_x [mm]": {
        "0": 4
      },
      "Rx_space_y [mm]": {
        "0": 1.2
      },
      "Rx_tap [mm]": {
        "0": 9
      },
      "Rx_turns [mm]": {
        "0": 2
      },
      "Rx_width [mm]": {
        "0": 1.1
      },
      "seed [mm]": {
        "0": 2116326268
      },
      "Tx_height [mm]": {
        "0": 0.105
      },
      "Tx_hTurns []": {
        "0": 7
      },
      "Tx_layer_space_x [mm]": {
        "0": 4.1
      },
      "Tx_layer_space_y [mm]": {
        "0": 4
      },
      "Tx_preg [mm]": {
        "0": 0.02
      },
      "Tx_space_x [mm]": {
        "0": 1.1
      },
      "Tx_space_y [mm]": {
        "0": 2
      },
      "Tx_tap [mm]": {
        "0": 31
      },
      "Tx_turns [mm]": {
        "0": 14
      },
      "Tx_width [mm]": {
        "0": 1.08
      },
      "w1 [mm]": {
        "0": 38
      },
      "Freq [kHz]": {
        "0": 140
      },
      "Matrix1.L(Tx1,Tx1) [uH]": {
        "0": 669.975578969215
      },
      "Matrix1.L(Rx1,Rx1) [uH]": {
        "0": 26.9753134713722
      },
      "Matrix1.L(Rx2,Rx2) [uH]": {
        "0": 26.9815241482202
      },
      "Matrix1.L(Tx1,Rx1) [uH]": {
        "0": -133.130947543812
      },
      "Matrix1.L(Tx1,Rx2) [uH]": {
        "0": -133.130248623607
      },
      "Matrix1.CplCoef(Tx1,Rx1) []": {
        "0": -0.990298877150741
      },
      "Matrix1.CplCoef(Tx1,Rx2) []": {
        "0": -0.990179697473587
      },
      "Matrix1.L(Tx1,Tx1)*(Matrix1.CplCoef(Tx1,Rx1)^2) [uH]": {
        "0": 657.03960077138
      },
      "Matrix1.L(Rx1,Rx1)*(Matrix1.CplCoef(Tx1,Rx1)^2) [uH]": {
        "0": 26.4544705064953
      },
      "Matrix1.L(Rx2,Rx2)*(Matrix1.CplCoef(Tx1,Rx2)^2) [uH]": {
        "0": 26.4541927421474
      },
      "Matrix1.L(Tx1,Tx1)*(1-Matrix1.CplCoef(Tx1,Rx1)^2) [uH]": {
        "0": 12.935978197835
      },
      "Matrix1.L(Rx1,Rx1)*(1-Matrix1.CplCoef(Tx1,Rx1)^2) [nH]": {
        "0": 520.842964876888
      },
      "Matrix1.L(Rx2,Rx2)*(1-Matrix1.CplCoef(Tx1,Rx2)^2) [nH]": {
        "0": 527.331406072791
      }
    },
    "_get_magnetic_report": {
      "Ltx_uH": 669.975578969215,
      "Lrx1_uH": 26.9753134713722,
      "Lrx2_uH": 26.9815241482202,
      "M1_uH": 133.130947543812,
      "M2_uH": 133.130248623607,
      "k1_uH": 0.990298877150741,
      "k2_uH": 0.990179697473587,
      "Lmt_uH": 657.03960077138,
      "Lmr1_uH": 26.4544705064953,
      "Lmr2_uH": 26.4541927421474,
      "Llt_uH": 12.935978197835,
      "Llr1_uH": 0.520842964876888,
      "Llr2_uH": 0.5273314060727909
    },
    "copper loss data": {
      "Freq [kHz]": {
        "0": 140
      },
      "Distance [mm]": {
        "0": 1
      },
      "P_Tx_1 []": {
        "0": 14.2398830800818
      },
      "Distance [mm].1": {
        "0": 1
      },
      "P_Rx_False_True_1 []": {
        "0": 10.0826644561125
      },
      "Distance [mm].2": {
        "0": 1
      },
      "P_Rx_True_True_1 []": {
        "0": 0.411458509010517
      }
    },
    "_get_copper_loss_parameter": {
      "P_Tx_1 []": 0,
      "P_Rx_False_True_1 []": 0,
      "P_Rx_True_True_1 []": 0
    },
    "coreloss parameter": {
      "A [mm]": {
        "0": 59.6
      },
      "B [mm]": {
        "0": 43.2
      },
      "C [mm]": {
        "0": 10.4
      },
      "core_N_w1 [mm]": {
        "0": 4
      },
      "core_P_w1 [mm]": {
        "0": 14
      },
      "D [mm]": {
        "0": 17.4
      },
      "E [mm]": {
        "0": 6.8
      },
      "g1 [mm]": {
        "0": 0.1
      },
      "g2 [mm]": {
        "0": 0.3
      },
      "h1 [mm]": {
        "0": 13.6
      },
      "l1_center [mm]": {
        "0": 10.4
      },
      "l1_leg [mm]": {
        "0": 8.2
      },
      "l1_top [mm]": {
        "0": 10.6
      },
      "l2 [mm]": {
        "0": 16.4
      },
      "l2_tap [mm]": {
        "0": 0
      },
      "ratio [mm]": {
        "0": 0.51
      },
      "Rx_height [mm]": {
        "0": 0.175
      },
      "Rx_hTurns []": {
        "0": 1
      },
      "Rx_layer_space_x [mm]": {
        "0": 2.9
      },
      "Rx_layer_space_y [mm]": {
        "0": 1.9
      },
      "Rx_preg [mm]": {
        "0": 0.01
      },
      "Rx_space_x [mm]": {
        "0": 4
      },
      "Rx_space_y [mm]": {
        "0": 1.2
      },
      "Rx_tap [mm]": {
        "0": 9
      },
      "Rx_turns [mm]": {
        "0": 2
      },
      "Rx_width [mm]": {
        "0": 1.1
      },
      "seed [mm]": {
        "0": 2116326268
      },
      "Tx_height [mm]": {
        "0": 0.105
      },
      "Tx_hTurns []": {
        "0": 7
      },
      "Tx_layer_space_x [mm]": {
        "0": 4.1
      },
      "Tx_layer_space_y [mm]": {
        "0": 4
      },
      "Tx_preg [mm]": {
        "0": 0.02
      },
      "Tx_space_x [mm]": {
        "0": 1.1
      },
      "Tx_space_y [mm]": {
        "0": 2
      },
      "Tx_tap [mm]": {
        "0": 31
      },
      "Tx_turns [mm]": {
        "0": 14
      },
      "Tx_width [mm]": {
        "0": 1.08
      },
      "w1 [mm]": {
        "0": 38
      },
      "Freq [kHz]": {
        "0": 140
      },
      "Coreloss [mW]": {
        "0": 426.333
      }
    },
    "coreloss_project": {
      "Coreloss [mW]": 0.426333
    },
    "B mean report": {
      "Freq [kHz]": {
        "0": 140
      },
      "Distance [mm]": {
        "0": 1
      },
      "B_mean_leg_left []": {
        "0": 0.0249410842261376
      },
      "Distance [mm].1": {
        "0": 1
      },
      "B_mean_leg_center []": {
        "0": 0.0527344913267509
      },
      "Distance [mm].2": {
        "0": 1
      },
      "B_mean_leg_right []": {
        "0": 0.035172003664953
      },
      "Distance [mm].3": {
        "0": 1
      },
      "B_mean_leg_top_left []": {
        "0": 0.026731486070167
      },
      "Distance [mm].4": {
        "0": 1
      },
      "B_mean_leg_bottom_left []": {
        "0": 0.0267783886265318
      },
      "Distance [mm].5": {
        "0": 1
      },
      "B_mean_leg_top_right []": {
        "0": 0.0268910725148561
      },
      "Distance [mm].6": {
        "0": 1
      },
      "B_mean_leg_bottom_right []": {
        "0": 0.0270997108016216
      }
    },
    "__get_B_field": {
      "B_mean_leg_left []": 0.0249410842261376,
      "B_mean_leg_center []": 0.0527344913267509,
      "B_mean_leg_right []": 0.035172003664953,
      "B_mean_leg_top_left []": 0.026731486070167,
      "B_mean_leg_bottom_left []": 0.0267783886265318,
      "B_mean_leg_top_right []": 0.0268910725148561,
      "B_mean_leg_bottom_right []": 0.0270997108016216
    }
  },
  "o3ds": {
    "core_base": "<ansys.aedt.core.modeler.cad.object_3d.Object3d object at 0x000001CA19FD9690>",
    "core_sub1": "<ansys.aedt.core.modeler.cad.object_3d.Object3d object at 0x000001CA19FD9660>",
    "core_sub2": "<ansys.aedt.core.modeler.cad.object_3d.Object3d object at 0x000001CA19FD9480>",
    "core_sub_g1": "<ansys.aedt.core.modeler.cad.object_3d.Object3d object at 0x000001CA19FD93C0>",
    "core_sub_g2": "<ansys.aedt.core.modeler.cad.object_3d.Object3d object at 0x000001CA19FD96F0>",
    "core_unite_sub_g1": "<ansys.aedt.core.modeler.cad.object_3d.Object3d object at 0x000001CA19FD9420>",
    "Tx_connect": "<ansys.aedt.core.modeler.cad.polylines.Polyline object at 0x000001CA19FD9300>",
    "Tx_1": "<ansys.aedt.core.modeler.cad.polylines.Polyline object at 0x000001CA19FD93F0>",
    "Tx_2": "<ansys.aedt.core.modeler.cad.object_3d.Object3d object at 0x000001CA19FD94B0>",
    "Rx_False_True_connect": "<ansys.aedt.core.modeler.cad.polylines.Polyline object at 0x000001CA1908F370>",
    "Rx_False_True_1": "<ansys.aedt.core.modeler.cad.polylines.Polyline object at 0x000001CA19FD9180>",
    "Rx_False_True_2": "<ansys.aedt.core.modeler.cad.object_3d.Object3d object at 0x000001CA19FDAC20>",
    "Rx_True_True_connect": "<ansys.aedt.core.modeler.cad.polylines.Polyline object at 0x000001CA1908EDD0>",
    "Rx_True_True_1": "<ansys.aedt.core.modeler.cad.polylines.Polyline object at 0x000001CA19FDAA10>",
    "Rx_True_True_2": "<ansys.aedt.core.modeler.cad.object_3d.Object3d object at 0x000001CA19FDAFE0>",
    "B_fields": [
      "<ansys.aedt.core.modeler.cad.object_3d.Object3d object at 0x000001CA1AD49DE0>",
      "<ansys.aedt.core.modeler.cad.object_3d.Object3d object at 0x000001CA1AD49630>",
      "<ansys.aedt.core.modeler.cad.object_3d.Object3d object at 0x000001CA1AD495A0>",
      "<ansys.aedt.core.modeler.cad.object_3d.Object3d object at 0x000001CA1AD4A440>",
      "<ansys.aedt.core.modeler.cad.object_3d.Object3d object at 0x000001CA1AD49F30>",
      "<ansys.aedt.core.modeler.cad.object_3d.Object3d object at 0x000001CA1B031240>",
      "<ansys.aedt.core.modeler.cad.object_3d.Object3d object at 0x000001CA1B031420>"
    ]
  },
  "progress": "",
  "progress_dict": {
    "2025-07-23 12:17:49": [
      "set_variable_byvalue",
      "0.0000s"
    ],
    "2025-07-23 12:17:50": [
      "set_variable_byrange",
      "0.2350s"
    ],
    "2025-07-23 12:18:04": [
      "validate_variable_4Core",
      "0.5160s"
    ],
    "2025-07-23 12:18:05": [
      "validate_variable_new",
      "1.7350s"
    ],
    "2025-07-23 12:18:06": [
      "validate_variable",
      "2.3440s"
    ],
    "2025-07-23 12:18:07": [
      "create_core",
      "1.6090s"
    ],
    "2025-07-23 12:18:08": [
      "validate_variable_4Tx",
      "0.9220s"
    ],
    "2025-07-23 12:18:09": [
      "validate_variable_4Rx",
      "1.0630s"
    ],
    "2025-07-23 12:18:13": [
      "create_winding_new",
      "0.5940s"
    ],
    "2025-07-23 12:18:14": [
      "assign_mesh",
      "0.0310s"
    ],
    "2025-07-23 12:18:21": [
      "create_excitation",
      "6.6100s"
    ],
    "2025-07-23 12:18:22": [
      "validate_design",
      "0.2030s"
    ],
    "2025-07-23 12:33:17": [
      "analyze_all",
      "895.2810s"
    ],
    "2025-07-23 12:33:18": [
      "get_input_parameter",
      "0.0000s"
    ],
    "2025-07-23 12:33:19": [
      "_get_copper_loss_parameter",
      "1.5780s"
    ],
    "2025-07-23 12:35:34": [
      "__create_B_field",
      "1.2660s"
    ],
    "2025-07-23 12:38:37": [
      "_get_mean_Bfield",
      "0.0310s"
    ],
    "2025-07-23 12:38:39": [
      "coreloss_project",
      "319.2500s"
    ]
  },
  "start_time_pretty": "2025-07-23 12:15:14",
  "start_time": "591511250000000",
  "end_time_pretty": "2025-07-23 12:38:39",
  "end_time": "592915734000000",
  "design_name": "xform_2_Design",
  "project_name": "xform_2_Project",
  "modeler": "<ansys.aedt.core.modeler.modeler_3d.Modeler3D object at 0x000001CA19057B80>",
  "v": {
    "w1": 38.0,
    "l1_leg": 8.2,
    "l1_top": 10.6,
    "l1_center": 10.4,
    "l2": 16.4,
    "h1": 13.6,
    "l2_tap": 0.0,
    "ratio": 0.51,
    "Tx_turns": 14.0,
    "Tx_tap": 31.0,
    "Tx_height": 0.105,
    "Tx_preg": 0.02,
    "Rx_turns": 2.0,
    "Rx_tap": 9.0,
    "Rx_height": 0.175,
    "Rx_preg": 0.01,
    "g1": 0.1,
    "g2": 0.3,
    "Tx_space_x": 1.1,
    "Tx_space_y": 2.0,
    "Rx_space_x": 4.0,
    "Rx_space_y": 1.2,
    "core_N_w1": 4.0,
    "core_P_w1": 14.0,
    "Tx_layer_space_x": 4.1,
    "Tx_layer_space_y": 4.0,
    "Rx_layer_space_x": 2.9,
    "Rx_layer_space_y": 1.9,
    "Tx_width": 1.08,
    "Rx_width": 1.1,
    "seed": 2116326268,
    "A": 59.599999999999994,
    "B": 43.199999999999996,
    "C": 10.4,
    "D": 17.4,
    "E": 6.8
  },
  "comments": [],
  "coils_main": [
    "Tx_1",
    "Rx_False_True_1",
    "Rx_True_True_1"
  ],
  "sim_global": {
    "sim": "<peetsfea.xformermaker.project1.project2.Project2 object at 0x000001CA661BF940>",
    "debugging": false
  },
  "r": {
    "w1": [
      2,
      52,
      1.2,
      1
    ],
    "l1_leg": [
      1,
      12,
      1.2,
      3
    ],
    "l1_top": [
      1,
      12,
      1.2,
      3
    ],
    "l1_center": [
      2,
      25,
      1.2,
      3
    ],
    "l2": [
      2,
      25,
      1.2,
      3
    ],
    "h1": [
      4,
      52,
      1.2,
      2
    ],
    "l2_tap": [
      0,
      0,
      1,
      0
    ],
    "ratio": [
      0.5,
      0.5,
      0.01,
      2
    ],
    "Tx_turns": [
      14,
      14,
      1,
      0
    ],
    "Tx_tap": [
      2,
      35,
      1,
      0
    ],
    "Tx_height": [
      0.035,
      0.175,
      0.035,
      3
    ],
    "Tx_preg": [
      0.01,
      0.1,
      0.01,
      2
    ],
    "Rx_turns": [
      2,
      2,
      1,
      0
    ],
    "Rx_tap": [
      2,
      35,
      1,
      0
    ],
    "Rx_height": [
      0.035,
      0.175,
      0.035,
      3
    ],
    "Rx_preg": [
      0.01,
      0.1,
      0.01,
      2
    ],
    "g1": [
      0.1,
      0.1,
      0.01,
      2
    ],
    "g2": [
      0,
      0.5,
      0.01,
      2
    ],
    "Tx_space_x": [
      0.1,
      7,
      0.1,
      2
    ],
    "Tx_space_y": [
      0.1,
      7,
      0.1,
      2
    ],
    "Rx_space_x": [
      0.1,
      5,
      0.1,
      1
    ],
    "Rx_space_y": [
      0.1,
      5,
      0.1,
      1
    ],
    "core_N_w1": [
      0,
      30,
      1,
      0
    ],
    "core_P_w1": [
      0,
      30,
      1,
      0
    ],
    "Tx_layer_space_x": [
      0.1,
      5,
      0.1,
      1
    ],
    "Tx_layer_space_y": [
      0.1,
      5,
      0.1,
      1
    ],
    "Rx_layer_space_x": [
      0.1,
      5,
      0.1,
      1
    ],
    "Rx_layer_space_y": [
      0.1,
      5,
      0.1,
      1
    ],
    "Tx_width": [
      0.1,
      12,
      0.01,
      2
    ],
    "Rx_width": [
      1,
      20,
      0.1,
      1
    ]
  },
  "mat": "<ansys.aedt.core.modules.material.Material object at 0x000001CA1908FE50>",
  "bp_point": [
    [
      0,
      0
    ],
    [
      0.05,
      20.32
    ],
    [
      0.06,
      35.08
    ],
    [
      0.07,
      55.3
    ],
    [
      0.08,
      80.4
    ],
    [
      0.09,
      111.05
    ],
    [
      0.1,
      156.79
    ],
    [
      0.2,
      1002.4
    ]
  ],
  "setting": {
    "cores": 1,
    "tasks": 1,
    "gpus": 1,
    "use_auto_settings": false
  },
  "Lmt_uH": 657.03960077138,
  "input_parameter": "     w1  l1_leg  l1_top  l1_center    l2    h1  l2_tap  ratio  Tx_turns  \\\n0  38.0     8.2    10.6       10.4  16.4  13.6     0.0   0.51      14.0   \n\n   Tx_tap  Tx_height  Tx_preg  Rx_turns  Rx_tap  Rx_height  Rx_preg   g1   g2  \\\n0    31.0      0.105     0.02       2.0     9.0      0.175     0.01  0.1  0.3   \n\n   Tx_space_x  Tx_space_y  Rx_space_x  Rx_space_y  core_N_w1  core_P_w1  \\\n0         1.1         2.0         4.0         1.2        4.0       14.0   \n\n   Tx_layer_space_x  Tx_layer_space_y  Rx_layer_space_x  Rx_layer_space_y  \\\n0               4.1               4.0               2.9               1.9   \n\n   Tx_width  Rx_width        seed     A     B     C     D    E  \n0      1.08       1.1  2116326268  59.6  43.2  10.4  17.4  6.8  ",
  "exception": null
}